{
  "meta": {
    "stableOrder": true
  },
  "lockfileVersion": 3,
  "ATTENTION": "THIS IS AN AUTOGENERATED FILE. DO NOT EDIT THIS FILE DIRECTLY.",
  "specifiers": {
    "@jg/push@1.1.1": "@jg/push@1.1.1",
    "@ohos/hamock@1.0.0": "@ohos/hamock@1.0.0",
    "@ohos/hypium@1.0.19": "@ohos/hypium@1.0.19",
    "pako@2.1.0": "pako@2.1.0"
  },
  "packages": {
    "@jg/push@1.1.1": {
      "name": "@jg/push",
      "version": "1.1.1",
      "integrity": "sha512-1TqTHLmjbniMCwYD3AJv6jR7KkCF9sulMApu7bnoPQURqiC9sAjFZzgRL+EC/N60mzAH6Mc+/SnEnEjtjVLXOw==",
      "resolved": "https://ohpm.openharmony.cn/ohpm/@jg/push/-/push-1.1.1.har",
      "registryType": "ohpm",
      "dependencies": {
        "pako": "2.1.0"
      }
    },
    "@ohos/hamock@1.0.0": {
      "name": "@ohos/hamock",
      "version": "1.0.0",
      "integrity": "sha512-K6lDPYc6VkKe6ZBNQa9aoG+ZZMiwqfcR/7yAVFSUGIuOAhPvCJAo9+t1fZnpe0dBRBPxj2bxPPbKh69VuyAtDg==",
      "resolved": "https://ohpm.openharmony.cn/ohpm/@ohos/hamock/-/hamock-1.0.0.har",
      "registryType": "ohpm"
    },
    "@ohos/hypium@1.0.19": {
      "name": "@ohos/hypium",
      "version": "1.0.19",
      "integrity": "sha512-cEjDgLFCm3cWZDeRXk7agBUkPqjWxUo6AQeiu0gEkb3J8ESqlduQLSIXeo3cCsm8U/asL7iKjF85ZyOuufAGSQ==",
      "resolved": "https://ohpm.openharmony.cn/ohpm/@ohos/hypium/-/hypium-1.0.19.har",
      "registryType": "ohpm"
    },
    "pako@2.1.0": {
      "name": "pako",
      "version": "2.1.0",
      "integrity": "sha512-w+eufiZ1WuJYgPXbV/PO3NCMEc3xqylkKHzp8bxp1uW4qaSNQUkwmLLEc3kKsfz8lpV1F8Ht3U1Cm+9Srog2ug==",
      "resolved": "https://ohpm.openharmony.cn/ohpm/pako/-/pako-2.1.0.tgz",
      "shasum": "266cc37f98c7d883545d11335c00fbd4062c9a86",
      "registryType": "ohpm"
    }
  }
}